.DS_Store
machnamh/.DS_Store
machnamh/__init__.py
machnamh/demo_data.py
machnamh/helper.py
machnamh/pre_process.py
machnamh/data/absolute.png
machnamh/data/count.png
machnamh/data/law_data.csv
machnamh_pkg/__init__.py
machnamh-0.0.1.dist-info/LICENSE
machnamh-0.0.1.dist-info/METADATA
machnamh-0.0.1.dist-info/WHEEL
machnamh-0.0.1.dist-info/top_level.txt
machnamh-0.0.1.dist-info/RECORD
