Metadata-Version: 2.1
Name: machnamh
Version: 0.0.1
Summary: An ipywidgets based package for detecting bias in ML data and Models
Home-page: https://github.com/aideenf/machnamh
Author: Aideen Farrell
Author-email: aideenf@hotmail.com
License: UNKNOWN
Platform: UNKNOWN
Classifier: Development Status :: 4 - Beta
Classifier: License :: OSI Approved :: MIT License
Classifier: Programming Language :: Python :: 3
Classifier: Programming Language :: Python :: 3.6
Classifier: Programming Language :: Python :: 3.7
Requires-Python: >=3.6
Requires-Dist: kaleido
Requires-Dist: numpy
Requires-Dist: matplotlib
Requires-Dist: seaborn
Requires-Dist: pandas
Requires-Dist: scikit-learn
Requires-Dist: pandas-profiling (>=2.9.0)
Requires-Dist: phik (>=0.10.0)
Requires-Dist: ipywidgets
Requires-Dist: plotly
Requires-Dist: ipyfilechooser
Requires-Dist: dill
Requires-Dist: IPython
Requires-Dist: shap
Requires-Dist: aequitas
Requires-Dist: scipy
Requires-Dist: typing (>=3.7.4.3)
Requires-Dist: benfordslaw (>=0.1.3)
Requires-Dist: missingno
